{
  "display_name": "pyDREAM MonoSQ Normalized (Scaled Solvent Weight)",
  "description": "pyDREAM MonoSQ Normalized (Scaled Solvent Weight)\n\nPurpose:\nScale-coupled-solvent MonoSQ variant for projects where the experimental solvent trace should be placed under the same global intensity scale as the MD-derived solute model. The original pyDREAM MonoSQ Normalized template remains available unchanged for projects that rely on the historical unscaled-solvent convention.\n\nStructure Factor:\nMonodisperse hard-sphere structure factor evaluated with calc_monodisperse_sq using the Percus-Yevick approximation. The effective particle size is controlled by eff_r and the hard-sphere packing term is controlled by vol_frac. The default eff_r is 3 A so new projects start at the lower bound instead of assuming a larger interaction radius before the user or fit has evidence for it.\n\nForm Factor:\nWeighted mixture of MD-derived SAXS component profiles assembled from the project's averaged cluster scattering curves. The weighted component mixture is multiplied by the hard-sphere structure factor. The solvent trace is multiplied by solv_w, added to the solute branch, and then the combined solute + solvent expression is multiplied by the global scale before adding offset.\n\nModel Equation:\nI_model(q) = scale * (sum_i w_i I_i(q) S_HS(q; eff_r, vol_frac) + solv_w * I_solv(q)) + offset\n\nCalculator Integration:\nThe solution-scattering estimator can pre-populate vol_frac from the physical solute-associated volume fraction, because vol_frac is the hard-sphere packing term rather than the solvent background multiplier. The estimator can also pre-populate solv_w with the combined solvent background multiplier. In this template solv_w is interpreted before the global scale is applied, so it can remain representative of a solvent-background fraction instead of compensating for the arbitrary MD model intensity scale.\n\nPrefit Startup:\nWhen this template is loaded with experimental data available, Prefit automatically applies its autoscale estimate to the scale and offset parameters unless a saved Best Prefit or current Prefit state already exists. The scale and offset limits are then centered around the autoscale result instead of preserving broad template-default bounds.\n\nLikelihood Convention:\nThe pyDREAM likelihood is normalized by the number of experimental points. This keeps the log-likelihood on a per-point basis so that its magnitude is less sensitive to changes in fitted q-range, resampling density, or dataset length.\n\nModel Parameters:\nw1, w2, ..., wN: Relative contribution of each MD-derived component profile.\nsolv_w: Solvent-background multiplier applied to the experimental solvent trace before the global scale is applied; its default range starts at [0, 1] and it is fixed by default for calculator-seeded workflows, but user-expanded bounds are preserved.\noffset: Additive baseline term used to capture residual background intensity.\neff_r: Effective hard-sphere radius used in the structure-factor calculation; defaults to 3 A.\nvol_frac: Hard-sphere packing fraction used in the Percus-Yevick structure factor; the solution-scattering estimator targets this field with the physical solute-associated volume fraction.\nscale: Multiplicative scale factor applied to the combined solute + weighted solvent contribution.",
  "capabilities": {
    "solution_scattering_estimator": {
      "volume_fraction_target": {
        "parameter": "vol_frac",
        "fraction_kind": "solute",
        "source": "physical"
      },
      "solvent_contribution_scale_mode": "global_scale"
    },
    "prefit": {
      "auto_apply_autoscale_on_load": true,
      "autoscale_bounds_mode": "adaptive"
    }
  }
}
